{
    "title": "35c3",
    "type": 0,
    "description": "The 35th Chaos Communication Congress (35C3) is an annual four-day conference on technology, society and utopia. The Congress offers lectures and workshops and various events on a multitude of topics including (but not limited to) information technology and generally a critical-creative attitude towards technology and the discussion about the effects of technological advances on society.",
    "website": "https://events.ccc.de/tag/35c3/",
    "country": "DE",
    "city": "Leipzig",
    "address": "Congress Center Leipzig",
    "starts": "2018-12-27T09:00:00+01:00",
    "ends": "2018-12-30T18:00:00+01:00",
    "tags": "35c3",
    "attributes": [
            "kids-friendly"
    ]
}

